cv2_gui/__init__.py
cv2_gui/cv2_gui.py
cv2_gui/setup.py
cv2_gui-0.6.7.dist-info/LICENSE
cv2_gui-0.6.7.dist-info/METADATA
cv2_gui-0.6.7.dist-info/WHEEL
cv2_gui-0.6.7.dist-info/top_level.txt
cv2_gui-0.6.7.dist-info/RECORD
