Metadata-Version: 2.1
Name: cv2-gui
Version: 0.6.7
Summary: A library to create buttons using OpenCV (cv2)
Home-page: https://github.com/Crystalazer/cv2_gui
Author: Tarun Shenoy
Author-email: tgshenoy1@gmail.com
License: MIT
Classifier: Programming Language :: Python :: 3
Classifier: License :: OSI Approved :: MIT License
Classifier: Operating System :: OS Independent
Requires-Python: >=3.6
License-File: LICENSE
Requires-Dist: opencv-contrib-python
Requires-Dist: numpy
